airless/email/__init__.py
airless/email/hook/__init__.py
airless/email/hook/email.py
airless/email/operator/__init__.py
airless/email/operator/email.py
airless_email-1.5.0.dist-info/METADATA
airless_email-1.5.0.dist-info/WHEEL
airless_email-1.5.0.dist-info/top_level.txt
airless_email-1.5.0.dist-info/RECORD
