Metadata-Version: 2.4
Name: airless-email
Version: 1.5.0
Summary: Airless package to manage email
License: MIT License
Project-URL: Homepage, https://github.com/astercapital/airless
Project-URL: Bug Tracker, https://github.com/astercapital/airless/issues
Requires-Python: >=3.9
Requires-Dist: airless-core<1.0.0,>=0.3.0
Requires-Dist: airless-google-cloud-storage>=0.2.0
